{
  "updatedAt": "2026-05-13T11:32:45.218Z",
  "createdAt": "2026-05-13T11:14:02.282Z",
  "id": "Z87bq4v2OFiy0FFV",
  "name": "Confirmacion de pago cliente v4",
  "active": true,
  "isArchived": false,
  "nodes": [
    {
      "parameters": {
        "path": "voy_a_pagar",
        "responseMode": "responseNode",
        "options": {}
      },
      "type": "n8n-nodes-base.webhook",
      "typeVersion": 2.1,
      "position": [
        -864,
        96
      ],
      "id": "1b277b90-f4b2-4748-ad43-88d30ea45be3",
      "name": "Webhook",
      "webhookId": "6ea94c0d-4f0d-40b4-936d-4dd61cf1d956"
    },
    {
      "parameters": {
        "sendTo": "contacta@hazmarca.es",
        "subject": "={{ $('Webhook').item.json.query.cliente }} va a pagar su {{ $('Webhook').item.json.query.dominio }} ",
        "message": "={{ $('Webhook').item.json.query.cliente }} va a pagar su {{ $('Webhook').item.json.query.dominio }}. Click en el boton para crear factura en FacturaScripts. Acción: mantener renovación automática en Sered.\n\n<div style=\"margin-top:24px;text-align:center\">\n  <a href=\"https://proyecton8n-n8n.yq3yuy.easypanel.host/webhook/el_cliente_ha_pagado?dominio={{ $('Webhook').item.json.query.dominio }}&codcliente={{ $('Webhook').item.json.query.codcliente }}&pvpunitario={{ $('Webhook').item.json.query.pvpunitario }}&cliente={{ $('Webhook').item.json.query.cliente }}\" style=\"background:#27AE60;color:white;padding:12px 24px;border-radius:6px;text-decoration:none;font-weight:bold;display:inline-block\">\n    Confirmo que el cliente ha pagado\n  </a>\n</div>",
        "options": {
          "appendAttribution": false
        }
      },
      "type": "n8n-nodes-base.gmail",
      "typeVersion": 2.2,
      "position": [
        80,
        80
      ],
      "id": "121c3262-2829-44f7-a03e-48c951ab6ee3",
      "name": "Send a message",
      "webhookId": "87246fd3-627d-4aea-8b14-cff29d1481d8",
      "credentials": {
        "gmailOAuth2": {
          "id": "K88Ro02qAPLqoTbF",
          "name": "Gmail contacta"
        }
      }
    },
    {
      "parameters": {
        "content": "## Webhook desde correo cliente\n",
        "height": 256,
        "width": 256,
        "color": "#3A3636"
      },
      "type": "n8n-nodes-base.stickyNote",
      "position": [
        -944,
        16
      ],
      "typeVersion": 1,
      "id": "b01e327e-8c1f-41c0-98ad-edc64eca813f",
      "name": "Sticky Note"
    },
    {
      "parameters": {
        "content": "## Enviar correo interno \n",
        "height": 256,
        "width": 272,
        "color": "#873636"
      },
      "type": "n8n-nodes-base.stickyNote",
      "position": [
        0,
        0
      ],
      "typeVersion": 1,
      "id": "aed6c9de-629a-4102-b0c7-26676271965b",
      "name": "Sticky Note2"
    },
    {
      "parameters": {
        "documentId": {
          "__rl": true,
          "value": "1QVP5U6uNJ7FdkoUwh4XXP_pZKzGfBbc8BZCSF_d_vs8",
          "mode": "list",
          "cachedResultName": "n8nRenovaciones",
          "cachedResultUrl": "https://docs.google.com/spreadsheets/d/1QVP5U6uNJ7FdkoUwh4XXP_pZKzGfBbc8BZCSF_d_vs8/edit?usp=drivesdk"
        },
        "sheetName": {
          "__rl": true,
          "value": "gid=0",
          "mode": "list",
          "cachedResultName": "Hoja 1",
          "cachedResultUrl": "https://docs.google.com/spreadsheets/d/1QVP5U6uNJ7FdkoUwh4XXP_pZKzGfBbc8BZCSF_d_vs8/edit#gid=0"
        },
        "filtersUI": {
          "values": [
            {
              "lookupColumn": "ID Cliente",
              "lookupValue": "={{ $json.query.codcliente }}"
            }
          ]
        },
        "options": {}
      },
      "type": "n8n-nodes-base.googleSheets",
      "typeVersion": 4.7,
      "position": [
        -656,
        96
      ],
      "id": "17f2ac85-3cbf-40ea-9058-99185211f227",
      "name": "Datos del Excel",
      "credentials": {
        "googleSheetsOAuth2Api": {
          "id": "tlryTl2TVc3G1dVp",
          "name": "Google Sheets account"
        }
      }
    },
    {
      "parameters": {
        "conditions": {
          "options": {
            "caseSensitive": true,
            "leftValue": "",
            "typeValidation": "strict",
            "version": 3
          },
          "conditions": [
            {
              "id": "41abf936-6221-48fd-a875-8f3e48b79d78",
              "leftValue": "={{ $json[\"Última Acción\"] }}",
              "rightValue": "",
              "operator": {
                "type": "string",
                "operation": "equals"
              }
            }
          ],
          "combinator": "or"
        },
        "options": {}
      },
      "type": "n8n-nodes-base.if",
      "typeVersion": 2.3,
      "position": [
        -496,
        96
      ],
      "id": "2853d86a-58fc-49ab-bfe7-c344f41db342",
      "name": "If"
    },
    {
      "parameters": {
        "respondWith": "json",
        "responseBody": "{\n  \"data\":\"Ya se está procesando\"\n}",
        "options": {}
      },
      "type": "n8n-nodes-base.respondToWebhook",
      "typeVersion": 1.5,
      "position": [
        -208,
        288
      ],
      "id": "2ff92952-4e94-487e-a8f3-360f14dc6dc0",
      "name": "Respond to Webhook"
    },
    {
      "parameters": {
        "operation": "update",
        "documentId": {
          "__rl": true,
          "value": "1QVP5U6uNJ7FdkoUwh4XXP_pZKzGfBbc8BZCSF_d_vs8",
          "mode": "list",
          "cachedResultName": "n8nRenovaciones",
          "cachedResultUrl": "https://docs.google.com/spreadsheets/d/1QVP5U6uNJ7FdkoUwh4XXP_pZKzGfBbc8BZCSF_d_vs8/edit?usp=drivesdk"
        },
        "sheetName": {
          "__rl": true,
          "value": "gid=0",
          "mode": "list",
          "cachedResultName": "Hoja 1",
          "cachedResultUrl": "https://docs.google.com/spreadsheets/d/1aV0k8akb8Bg65svTa5GPj_KHllcg2U2PuvvBkaNVLSk/edit#gid=0"
        },
        "columns": {
          "mappingMode": "defineBelow",
          "value": {
            "ID Cliente": "={{ $json[\"ID Cliente\"] }}",
            "Última Acción": "PENDIENTE"
          },
          "matchingColumns": [
            "ID Cliente"
          ],
          "schema": [
            {
              "id": "Dominio",
              "displayName": "Dominio",
              "required": false,
              "defaultMatch": false,
              "display": true,
              "type": "string",
              "canBeUsedToMatch": true,
              "removed": true
            },
            {
              "id": "Email Cliente",
              "displayName": "Email Cliente",
              "required": false,
              "defaultMatch": false,
              "display": true,
              "type": "string",
              "canBeUsedToMatch": true,
              "removed": true
            },
            {
              "id": "Fecha Vencimiento",
              "displayName": "Fecha Vencimiento",
              "required": false,
              "defaultMatch": false,
              "display": true,
              "type": "string",
              "canBeUsedToMatch": true,
              "removed": true
            },
            {
              "id": "Estado",
              "displayName": "Estado",
              "required": false,
              "defaultMatch": false,
              "display": true,
              "type": "string",
              "canBeUsedToMatch": true,
              "removed": true
            },
            {
              "id": "Precio Base (€)",
              "displayName": "Precio Base (€)",
              "required": false,
              "defaultMatch": false,
              "display": true,
              "type": "string",
              "canBeUsedToMatch": true,
              "removed": true
            },
            {
              "id": "ID Cliente",
              "displayName": "ID Cliente",
              "required": false,
              "defaultMatch": false,
              "display": true,
              "type": "string",
              "canBeUsedToMatch": true,
              "removed": false
            },
            {
              "id": "Nombre Cliente",
              "displayName": "Nombre Cliente",
              "required": false,
              "defaultMatch": false,
              "display": true,
              "type": "string",
              "canBeUsedToMatch": true,
              "removed": true
            },
            {
              "id": "Última Acción",
              "displayName": "Última Acción",
              "required": false,
              "defaultMatch": false,
              "display": true,
              "type": "string",
              "canBeUsedToMatch": true
            },
            {
              "id": "row_number",
              "displayName": "row_number",
              "required": false,
              "defaultMatch": false,
              "display": true,
              "type": "number",
              "canBeUsedToMatch": true,
              "readOnly": true,
              "removed": true
            }
          ],
          "attemptToConvertTypes": false,
          "convertFieldsToString": false
        },
        "options": {}
      },
      "type": "n8n-nodes-base.googleSheets",
      "typeVersion": 4.7,
      "position": [
        -208,
        80
      ],
      "id": "2c570ec1-b3f6-474a-8c41-6501f785337a",
      "name": "Datos del Excel1",
      "credentials": {
        "googleSheetsOAuth2Api": {
          "id": "tlryTl2TVc3G1dVp",
          "name": "Google Sheets account"
        }
      }
    }
  ],
  "connections": {
    "Webhook": {
      "main": [
        [
          {
            "node": "Datos del Excel",
            "type": "main",
            "index": 0
          }
        ]
      ]
    },
    "Datos del Excel": {
      "main": [
        [
          {
            "node": "If",
            "type": "main",
            "index": 0
          }
        ]
      ]
    },
    "If": {
      "main": [
        [
          {
            "node": "Respond to Webhook",
            "type": "main",
            "index": 0
          },
          {
            "node": "Datos del Excel1",
            "type": "main",
            "index": 0
          }
        ],
        [
          {
            "node": "Respond to Webhook",
            "type": "main",
            "index": 0
          }
        ]
      ]
    },
    "Datos del Excel1": {
      "main": [
        [
          {
            "node": "Send a message",
            "type": "main",
            "index": 0
          }
        ]
      ]
    }
  },
  "settings": {
    "executionOrder": "v1",
    "binaryMode": "separate",
    "timeSavedMode": "fixed",
    "errorWorkflow": "jWOwPrw3rbQy2Doq",
    "callerPolicy": "workflowsFromSameOwner",
    "availableInMCP": false
  },
  "staticData": null,
  "meta": {
    "templateCredsSetupCompleted": true
  },
  "pinData": {
    "Webhook": [
      {
        "json": {
          "headers": {
            "host": "proyecton8n-n8n.yq3yuy.easypanel.host",
            "user-agent": "Mozilla/5.0 (Windows NT 10.0; Win64; x64) AppleWebKit/537.36 (KHTML, like Gecko) Chrome/147.0.0.0 Safari/537.36",
            "accept": "text/html,application/xhtml+xml,application/xml;q=0.9,image/avif,image/webp,image/apng,*/*;q=0.8,application/signed-exchange;v=b3;q=0.7",
            "accept-encoding": "gzip, deflate, br, zstd",
            "accept-language": "es-ES,es;q=0.9,en;q=0.8",
            "cookie": {
              "__redacted": true,
              "reason": "node_defined_field",
              "canReveal": false
            },
            "priority": "u=0, i",
            "sec-ch-ua": "\"Google Chrome\";v=\"147\", \"Not.A/Brand\";v=\"8\", \"Chromium\";v=\"147\"",
            "sec-ch-ua-mobile": "?0",
            "sec-ch-ua-platform": "\"Windows\"",
            "sec-fetch-dest": "document",
            "sec-fetch-mode": "navigate",
            "sec-fetch-site": "cross-site",
            "sec-fetch-user": "?1",
            "upgrade-insecure-requests": "1",
            "x-forwarded-for": "78.30.9.5",
            "x-forwarded-host": "proyecton8n-n8n.yq3yuy.easypanel.host",
            "x-forwarded-port": "443",
            "x-forwarded-proto": "https",
            "x-forwarded-server": "946ec7fcaaf0",
            "x-real-ip": "78.30.9.5"
          },
          "params": {},
          "query": {
            "dominio": "dominio.eu",
            "idpresupuesto": "198",
            "codcliente": "41859",
            "pvpunitario": "71.2",
            "cliente": "LEANDRO MARTINEZ DEL RIO"
          },
          "body": {},
          "webhookUrl": "https://proyecton8n-n8n.yq3yuy.easypanel.host/webhook/voy_a_pagar",
          "executionMode": "production"
        },
        "pairedItem": {
          "item": 0
        }
      }
    ]
  },
  "versionId": "fe3738e0-bbaf-47b6-a59c-ce865c3e01f8",
  "activeVersionId": "fe3738e0-bbaf-47b6-a59c-ce865c3e01f8",
  "triggerCount": 1,
  "shared": [
    {
      "updatedAt": "2026-05-13T11:14:02.286Z",
      "createdAt": "2026-05-13T11:14:02.286Z",
      "role": "workflow:owner",
      "workflowId": "Z87bq4v2OFiy0FFV",
      "projectId": "HySVhA2Rl8waskJL"
    }
  ],
  "activeVersion": {
    "updatedAt": "2026-05-13T11:33:13.000Z",
    "createdAt": "2026-05-13T11:32:45.219Z",
    "versionId": "fe3738e0-bbaf-47b6-a59c-ce865c3e01f8",
    "workflowId": "Z87bq4v2OFiy0FFV",
    "nodes": [
      {
        "parameters": {
          "path": "voy_a_pagar",
          "responseMode": "responseNode",
          "options": {}
        },
        "type": "n8n-nodes-base.webhook",
        "typeVersion": 2.1,
        "position": [
          -864,
          96
        ],
        "id": "1b277b90-f4b2-4748-ad43-88d30ea45be3",
        "name": "Webhook",
        "webhookId": "6ea94c0d-4f0d-40b4-936d-4dd61cf1d956"
      },
      {
        "parameters": {
          "sendTo": "contacta@hazmarca.es",
          "subject": "={{ $('Webhook').item.json.query.cliente }} va a pagar su {{ $('Webhook').item.json.query.dominio }} ",
          "message": "={{ $('Webhook').item.json.query.cliente }} va a pagar su {{ $('Webhook').item.json.query.dominio }}. Click en el boton para crear factura en FacturaScripts. Acción: mantener renovación automática en Sered.\n\n<div style=\"margin-top:24px;text-align:center\">\n  <a href=\"https://proyecton8n-n8n.yq3yuy.easypanel.host/webhook/el_cliente_ha_pagado?dominio={{ $('Webhook').item.json.query.dominio }}&codcliente={{ $('Webhook').item.json.query.codcliente }}&pvpunitario={{ $('Webhook').item.json.query.pvpunitario }}&cliente={{ $('Webhook').item.json.query.cliente }}\" style=\"background:#27AE60;color:white;padding:12px 24px;border-radius:6px;text-decoration:none;font-weight:bold;display:inline-block\">\n    Confirmo que el cliente ha pagado\n  </a>\n</div>",
          "options": {
            "appendAttribution": false
          }
        },
        "type": "n8n-nodes-base.gmail",
        "typeVersion": 2.2,
        "position": [
          80,
          80
        ],
        "id": "121c3262-2829-44f7-a03e-48c951ab6ee3",
        "name": "Send a message",
        "webhookId": "87246fd3-627d-4aea-8b14-cff29d1481d8",
        "credentials": {
          "gmailOAuth2": {
            "id": "K88Ro02qAPLqoTbF",
            "name": "Gmail contacta"
          }
        }
      },
      {
        "parameters": {
          "content": "## Webhook desde correo cliente\n",
          "height": 256,
          "width": 256,
          "color": "#3A3636"
        },
        "type": "n8n-nodes-base.stickyNote",
        "position": [
          -944,
          16
        ],
        "typeVersion": 1,
        "id": "b01e327e-8c1f-41c0-98ad-edc64eca813f",
        "name": "Sticky Note"
      },
      {
        "parameters": {
          "content": "## Enviar correo interno \n",
          "height": 256,
          "width": 272,
          "color": "#873636"
        },
        "type": "n8n-nodes-base.stickyNote",
        "position": [
          0,
          0
        ],
        "typeVersion": 1,
        "id": "aed6c9de-629a-4102-b0c7-26676271965b",
        "name": "Sticky Note2"
      },
      {
        "parameters": {
          "documentId": {
            "__rl": true,
            "value": "1QVP5U6uNJ7FdkoUwh4XXP_pZKzGfBbc8BZCSF_d_vs8",
            "mode": "list",
            "cachedResultName": "n8nRenovaciones",
            "cachedResultUrl": "https://docs.google.com/spreadsheets/d/1QVP5U6uNJ7FdkoUwh4XXP_pZKzGfBbc8BZCSF_d_vs8/edit?usp=drivesdk"
          },
          "sheetName": {
            "__rl": true,
            "value": "gid=0",
            "mode": "list",
            "cachedResultName": "Hoja 1",
            "cachedResultUrl": "https://docs.google.com/spreadsheets/d/1QVP5U6uNJ7FdkoUwh4XXP_pZKzGfBbc8BZCSF_d_vs8/edit#gid=0"
          },
          "filtersUI": {
            "values": [
              {
                "lookupColumn": "ID Cliente",
                "lookupValue": "={{ $json.query.codcliente }}"
              }
            ]
          },
          "options": {}
        },
        "type": "n8n-nodes-base.googleSheets",
        "typeVersion": 4.7,
        "position": [
          -656,
          96
        ],
        "id": "17f2ac85-3cbf-40ea-9058-99185211f227",
        "name": "Datos del Excel",
        "credentials": {
          "googleSheetsOAuth2Api": {
            "id": "tlryTl2TVc3G1dVp",
            "name": "Google Sheets account"
          }
        }
      },
      {
        "parameters": {
          "conditions": {
            "options": {
              "caseSensitive": true,
              "leftValue": "",
              "typeValidation": "strict",
              "version": 3
            },
            "conditions": [
              {
                "id": "41abf936-6221-48fd-a875-8f3e48b79d78",
                "leftValue": "={{ $json[\"Última Acción\"] }}",
                "rightValue": "",
                "operator": {
                  "type": "string",
                  "operation": "equals"
                }
              }
            ],
            "combinator": "or"
          },
          "options": {}
        },
        "type": "n8n-nodes-base.if",
        "typeVersion": 2.3,
        "position": [
          -496,
          96
        ],
        "id": "2853d86a-58fc-49ab-bfe7-c344f41db342",
        "name": "If"
      },
      {
        "parameters": {
          "respondWith": "json",
          "responseBody": "{\n  \"data\":\"Ya se está procesando\"\n}",
          "options": {}
        },
        "type": "n8n-nodes-base.respondToWebhook",
        "typeVersion": 1.5,
        "position": [
          -208,
          288
        ],
        "id": "2ff92952-4e94-487e-a8f3-360f14dc6dc0",
        "name": "Respond to Webhook"
      },
      {
        "parameters": {
          "operation": "update",
          "documentId": {
            "__rl": true,
            "value": "1QVP5U6uNJ7FdkoUwh4XXP_pZKzGfBbc8BZCSF_d_vs8",
            "mode": "list",
            "cachedResultName": "n8nRenovaciones",
            "cachedResultUrl": "https://docs.google.com/spreadsheets/d/1QVP5U6uNJ7FdkoUwh4XXP_pZKzGfBbc8BZCSF_d_vs8/edit?usp=drivesdk"
          },
          "sheetName": {
            "__rl": true,
            "value": "gid=0",
            "mode": "list",
            "cachedResultName": "Hoja 1",
            "cachedResultUrl": "https://docs.google.com/spreadsheets/d/1aV0k8akb8Bg65svTa5GPj_KHllcg2U2PuvvBkaNVLSk/edit#gid=0"
          },
          "columns": {
            "mappingMode": "defineBelow",
            "value": {
              "ID Cliente": "={{ $json[\"ID Cliente\"] }}",
              "Última Acción": "PENDIENTE"
            },
            "matchingColumns": [
              "ID Cliente"
            ],
            "schema": [
              {
                "id": "Dominio",
                "displayName": "Dominio",
                "required": false,
                "defaultMatch": false,
                "display": true,
                "type": "string",
                "canBeUsedToMatch": true,
                "removed": true
              },
              {
                "id": "Email Cliente",
                "displayName": "Email Cliente",
                "required": false,
                "defaultMatch": false,
                "display": true,
                "type": "string",
                "canBeUsedToMatch": true,
                "removed": true
              },
              {
                "id": "Fecha Vencimiento",
                "displayName": "Fecha Vencimiento",
                "required": false,
                "defaultMatch": false,
                "display": true,
                "type": "string",
                "canBeUsedToMatch": true,
                "removed": true
              },
              {
                "id": "Estado",
                "displayName": "Estado",
                "required": false,
                "defaultMatch": false,
                "display": true,
                "type": "string",
                "canBeUsedToMatch": true,
                "removed": true
              },
              {
                "id": "Precio Base (€)",
                "displayName": "Precio Base (€)",
                "required": false,
                "defaultMatch": false,
                "display": true,
                "type": "string",
                "canBeUsedToMatch": true,
                "removed": true
              },
              {
                "id": "ID Cliente",
                "displayName": "ID Cliente",
                "required": false,
                "defaultMatch": false,
                "display": true,
                "type": "string",
                "canBeUsedToMatch": true,
                "removed": false
              },
              {
                "id": "Nombre Cliente",
                "displayName": "Nombre Cliente",
                "required": false,
                "defaultMatch": false,
                "display": true,
                "type": "string",
                "canBeUsedToMatch": true,
                "removed": true
              },
              {
                "id": "Última Acción",
                "displayName": "Última Acción",
                "required": false,
                "defaultMatch": false,
                "display": true,
                "type": "string",
                "canBeUsedToMatch": true
              },
              {
                "id": "row_number",
                "displayName": "row_number",
                "required": false,
                "defaultMatch": false,
                "display": true,
                "type": "number",
                "canBeUsedToMatch": true,
                "readOnly": true,
                "removed": true
              }
            ],
            "attemptToConvertTypes": false,
            "convertFieldsToString": false
          },
          "options": {}
        },
        "type": "n8n-nodes-base.googleSheets",
        "typeVersion": 4.7,
        "position": [
          -208,
          80
        ],
        "id": "2c570ec1-b3f6-474a-8c41-6501f785337a",
        "name": "Datos del Excel1",
        "credentials": {
          "googleSheetsOAuth2Api": {
            "id": "tlryTl2TVc3G1dVp",
            "name": "Google Sheets account"
          }
        }
      }
    ],
    "connections": {
      "Webhook": {
        "main": [
          [
            {
              "node": "Datos del Excel",
              "type": "main",
              "index": 0
            }
          ]
        ]
      },
      "Datos del Excel": {
        "main": [
          [
            {
              "node": "If",
              "type": "main",
              "index": 0
            }
          ]
        ]
      },
      "If": {
        "main": [
          [
            {
              "node": "Respond to Webhook",
              "type": "main",
              "index": 0
            },
            {
              "node": "Datos del Excel1",
              "type": "main",
              "index": 0
            }
          ],
          [
            {
              "node": "Respond to Webhook",
              "type": "main",
              "index": 0
            }
          ]
        ]
      },
      "Datos del Excel1": {
        "main": [
          [
            {
              "node": "Send a message",
              "type": "main",
              "index": 0
            }
          ]
        ]
      }
    },
    "authors": "Leandro Martinez",
    "name": "Version fe3738e0",
    "description": "",
    "autosaved": true
  },
  "tags": [
    {
      "updatedAt": "2026-05-11T09:01:50.331Z",
      "createdAt": "2026-05-11T09:01:50.331Z",
      "id": "1RdtjEkS3P0u2ppX",
      "name": "v4"
    }
  ]
}